pynball/__init__.py
pynball/pynball.py
pynball-1.5.7.dist-info/LICENSE
pynball-1.5.7.dist-info/METADATA
pynball-1.5.7.dist-info/WHEEL
pynball-1.5.7.dist-info/entry_points.txt
pynball-1.5.7.dist-info/top_level.txt
pynball-1.5.7.dist-info/RECORD
