Metadata-Version: 2.1
Name: pynball
Version: 1.5.7
Summary: Utility command line tool to manage python versions and virtual environments
Home-page: https://github.com/stephen-ra-king/pynball
Download-URL: 
Author: Stephen R A King
Author-email: sking.github@gmail.com
Maintainer: Stephen R A King
Maintainer-email: sking.github@gmail.com
License: MIT
Project-URL: documentation, https://pynamer.readthedocs.io/en/latest/
Project-URL: Release Notes, https://github.com/Stephen-RA-King/pynamer/releases
Project-URL: Source Code, https://github.com/Stephen-RA-King/pynamer/
Project-URL: Issue Tracker, https://github.com/Stephen-RA-King/pynamer/issues
Keywords: python-version-management,python-version-manager,virtualenv-manager,python-version-selector,python-versions,python-environment
Platform: windows
Classifier: Development Status :: 5 - Production/Stable
Classifier: Environment :: Console
Classifier: Intended Audience :: Developers
Classifier: License :: OSI Approved :: MIT License
Classifier: Operating System :: Microsoft :: Windows
Classifier: Topic :: System :: Installation/Setup
Classifier: Natural Language :: English
Classifier: Programming Language :: Python :: 3
Classifier: Programming Language :: Python :: 3 :: Only
Classifier: Programming Language :: Python :: 3.8
Classifier: Programming Language :: Python :: 3.9
Classifier: Programming Language :: Python :: 3.10
Classifier: Programming Language :: Python :: 3.11
Requires-Python: >=3.8
License-File: LICENSE
Requires-Dist: click (<8.2.0,>=8.1.3)
Requires-Dist: python-magic-bin (==0.4.14) ; platform_system == "Windows"
